maplex/__init__.py
maplex/mapleColors.py
maplex/mapleExceptions.py
maplex/mapleLogger.py
maplex/mapleTreeEditor.py
maplex/utils.py
maplex-2.0.0.dist-info/licenses/LICENSE
maplex-2.0.0.dist-info/METADATA
maplex-2.0.0.dist-info/WHEEL
maplex-2.0.0.dist-info/top_level.txt
maplex-2.0.0.dist-info/RECORD
