Metadata-Version: 2.4
Name: MapleX
Version: 2.0.0
Summary: MapleX: A Python library for Maple file format operations, with logging and console color utilities
Author: Ryuji Hazama
License: MIT
Classifier: Programming Language :: Python :: 3.11
Classifier: License :: OSI Approved :: MIT License
Classifier: Operating System :: OS Independent
Requires-Python: >=3.8
License-File: LICENSE
Requires-Dist: cryptography>=46.0.3
Requires-Dist: pydantic>=2.12.5
Dynamic: license-file
Dynamic: requires-python
